django_saml2_auth/__init__.py
django_saml2_auth/errors.py
django_saml2_auth/exceptions.py
django_saml2_auth/saml.py
django_saml2_auth/urls.py
django_saml2_auth/user.py
django_saml2_auth/utils.py
django_saml2_auth/views.py
django_saml2_auth/templates/django_saml2_auth/denied.html
django_saml2_auth/templates/django_saml2_auth/error.html
django_saml2_auth/templates/django_saml2_auth/signout.html
django_saml2_auth/tests/__init__.py
django_saml2_auth/tests/dummy_cert.pem
django_saml2_auth/tests/dummy_key.pem
django_saml2_auth/tests/metadata.xml
django_saml2_auth/tests/metadata2.xml
django_saml2_auth/tests/settings.py
django_saml2_auth/tests/test_saml.py
django_saml2_auth/tests/test_user.py
django_saml2_auth/tests/test_utils.py
grafana_django_saml2_auth-3.20.0.dist-info/METADATA
grafana_django_saml2_auth-3.20.0.dist-info/WHEEL
grafana_django_saml2_auth-3.20.0.dist-info/licenses/AUTHORS.md
grafana_django_saml2_auth-3.20.0.dist-info/licenses/LICENSE
grafana_django_saml2_auth-3.20.0.dist-info/RECORD
